var greenlawhall = {
"type": "FeatureCollection",
"crs": { "type": "name", "properties": { "name": "urn:ogc:def:crs:OGC:1.3:CRS84" } },
"features": [
{ "type": "Feature", "properties": { "id": 1, "descrip": "greenlawhall" }, "geometry": { "type": "Point", "coordinates": [-79.049331, 35.910416 ] } }
]
}
